MyFileInfoLib/MyFileInfoLibClass.py
MyFileInfoLib/__init__.py
MyFileInfoLib-0.2.dist-info/LICENSE
MyFileInfoLib-0.2.dist-info/METADATA
MyFileInfoLib-0.2.dist-info/WHEEL
MyFileInfoLib-0.2.dist-info/top_level.txt
MyFileInfoLib-0.2.dist-info/RECORD
