Metadata-Version: 2.1
Name: MyFileInfoLib
Version: 0.2
Summary: This library gets some information about a couple of files.
Home-page: https://github.com/alina-filippova/MyFileInfoLib.git
Author: Alina Filippova
Author-email: alia.filippova.2002k@mail.ru
License: UNKNOWN
Platform: UNKNOWN
Requires-Python: >=3.9
